impulse/__init__.py
impulse/indirect.py
impulse/solver.py
impulse/yolov5/__init__.py
impulse/yolov5/yolov5.py
impulse/yolov5/models/coco128.yaml
impulse/yolov5/models/common.py
impulse/yolov5/models/experimental.py
impulse/yolov5/models/yolo.py
impulse/yolov5/utils/activations.py
impulse/yolov5/utils/augmentations.py
impulse/yolov5/utils/autoanchor.py
impulse/yolov5/utils/autobatch.py
impulse/yolov5/utils/callbacks.py
impulse/yolov5/utils/datasets.py
impulse/yolov5/utils/downloads.py
impulse/yolov5/utils/general.py
impulse/yolov5/utils/loss.py
impulse/yolov5/utils/metrics.py
impulse/yolov5/utils/plots.py
impulse/yolov5/utils/torch_utils.py
Captcha_Impulse-0.0.9.dist-info/LICENSE
Captcha_Impulse-0.0.9.dist-info/METADATA
Captcha_Impulse-0.0.9.dist-info/WHEEL
Captcha_Impulse-0.0.9.dist-info/top_level.txt
Captcha_Impulse-0.0.9.dist-info/RECORD
